helpman/__init__.py
helpman/__version__.py
helpman/pyhelp.1.py
helpman/pyhelp.py
helpman-2.33.dist-info/METADATA
helpman-2.33.dist-info/WHEEL
helpman-2.33.dist-info/entry_points.txt
helpman-2.33.dist-info/top_level.txt
helpman-2.33.dist-info/RECORD
