Metadata-Version: 2.4
Name: helpman
Version: 2.33
Summary: Enhanced Python Help Tool with Rich Library - Beautiful terminal output.
Home-page: https://github.com/cumulus13/pyhelp
Author: Hadi Cahyadi
Author-email: cumulus13@gmail.com
Project-URL: Bug Reports, https://github.com/cumulus13/pyhelp/issues
Project-URL: Source, https://github.com/cumulus13/pyhelp
Project-URL: Documentation, https://github.com/cumulus13/pyhelp#readme
Keywords: Help Tool Rich Beautiful terminal
Classifier: Development Status :: 4 - Beta
Classifier: Intended Audience :: Developers
Classifier: License :: OSI Approved :: MIT License
Classifier: Operating System :: OS Independent
Classifier: Programming Language :: Python :: 3
Classifier: Programming Language :: Python :: 3.7
Classifier: Programming Language :: Python :: 3.8
Classifier: Programming Language :: Python :: 3.9
Classifier: Programming Language :: Python :: 3.10
Classifier: Programming Language :: Python :: 3.11
Classifier: Programming Language :: Python :: 3.12
Classifier: Topic :: Software Development :: Libraries :: Python Modules
Classifier: Topic :: Utilities
Requires-Python: >=3.7
Requires-Dist: rich>=10.0.0
Requires-Dist: licface
Requires-Dist: rich_argparse
Dynamic: author
Dynamic: author-email
Dynamic: classifier
Dynamic: description
Dynamic: description-content-type
Dynamic: home-page
Dynamic: keywords
Dynamic: project-url
Dynamic: requires-dist
Dynamic: requires-python
Dynamic: summary
